parkitect_blueprint_reader/__init__.py
parkitect_blueprint_reader/__version__.py
parkitect_blueprint_reader/blueprint.py
parkitect_blueprint_reader/cli.py
parkitect_blueprint_reader-1.1.2.dist-info/licenses/LICENSE.md
parkitect_blueprint_reader-1.1.2.dist-info/METADATA
parkitect_blueprint_reader-1.1.2.dist-info/WHEEL
parkitect_blueprint_reader-1.1.2.dist-info/entry_points.txt
parkitect_blueprint_reader-1.1.2.dist-info/top_level.txt
parkitect_blueprint_reader-1.1.2.dist-info/RECORD
