Metadata-Version: 2.4
Name: parkitect-blueprint-reader
Version: 1.1.2
Summary: Python API and CLI tool to read Parkitect's blueprints metadata.
Home-page: https://github.com/EpocDotFr/parkitect-blueprint-reader
Author: Maxime "Epoc" Gross
Author-email: contact.nospam@epoc.nospam.fr
License: DBAD
Project-URL: Documentation, https://github.com/EpocDotFr/parkitect-blueprint-reader?tab=readme-ov-file#usage
Project-URL: Source code, https://github.com/EpocDotFr/parkitect-blueprint-reader
Project-URL: Issue tracker, https://github.com/EpocDotFr/parkitect-blueprint-reader/issues
Project-URL: Changelog, https://github.com/EpocDotFr/parkitect-blueprint-reader/releases
Keywords: parkitect,blueprint,reader,steganography
Classifier: Development Status :: 5 - Production/Stable
Classifier: Operating System :: OS Independent
Classifier: Environment :: Console
Classifier: Topic :: Games/Entertainment
Classifier: Topic :: File Formats
Classifier: Topic :: Multimedia :: Graphics
Classifier: Programming Language :: Python :: 3.10
Classifier: Programming Language :: Python :: 3.11
Classifier: Programming Language :: Python :: 3.12
Classifier: Intended Audience :: Developers
Requires-Python: >=3.10
License-File: LICENSE.md
Requires-Dist: pillow~=11.1
Requires-Dist: bitstring~=4.3
Provides-Extra: dev
Requires-Dist: setuptools>=69; extra == "dev"
Requires-Dist: build~=1.2; extra == "dev"
Requires-Dist: twine~=6.0; extra == "dev"
Dynamic: author
Dynamic: author-email
Dynamic: classifier
Dynamic: description
Dynamic: description-content-type
Dynamic: home-page
Dynamic: keywords
Dynamic: license
Dynamic: license-file
Dynamic: project-url
Dynamic: provides-extra
Dynamic: requires-dist
Dynamic: requires-python
Dynamic: summary
